{"paths": [{"d": "M886 708 L857 759", "elementId": "lever_base"}, {"d": "M891 713 L862 763", "elementId": "lever_base"}, {"d": "M936 652 L856 792", "elementId": "lever_base"}, {"d": "M974 742 L963 739 L964 752", "elementId": "lever_base"}, {"d": "M933 794 L911 805 L933 819", "elementId": "lever_base"}, {"d": "M909 776 L902 797 L909 836", "elementId": "lever_base"}, {"d": "M911 766 L898 797 L907 837", "elementId": "lever_base"}, {"d": "M854 773 L827 822", "elementId": "lever_base"}, {"d": "M843 816 L823 850", "elementId": "lever_base"}, {"d": "M826 825 L816 851", "elementId": "lever_base"}, {"d": "M814 856 L796 888", "elementId": "lever_base"}, {"d": "M821 823 L768 917", "elementId": "lever_base"}, {"d": "M821 868 L786 924", "elementId": "lever_base"}, {"d": "M825 941 L797 942", "elementId": "lever_base"}, {"d": "M766 933 L711 935", "elementId": "lever_base"}, {"d": "M937 927 L833 932", "elementId": "lever_base"}, {"d": "M939 933 L908 935", "elementId": "lever_base"}, {"d": "M983 945 L904 946", "elementId": "lever_base"}, {"d": "M909 941 L994 941", "elementId": "lever_base"}, {"d": "M992 931 L951 932", "elementId": "lever_base"}, {"d": "M1012 931 L1046 932", "elementId": "lever_base"}, {"d": "M1055 937 L1011 941", "elementId": "lever_base"}, {"d": "M1060 936 L1124 936", "elementId": "lever_base"}, {"d": "M1133 925 L1049 930", "elementId": "lever_base"}, {"d": "M1126 938 L1153 941", "elementId": "lever_base"}, {"d": "M1227 933 L1164 934", "elementId": "lever_base"}, {"d": "M1107 821 L1133 867", "elementId": "lever_base"}, {"d": "M1101 825 L1126 871", "elementId": "lever_base"}, {"d": "M1056 758 L1128 890", "elementId": "lever_base"}, {"d": "M1022 844 L1018 853 L1007 845", "elementId": "lever_base"}, {"d": "M997 813 L1008 839", "elementId": "lever_base"}, {"d": "M697 725 L670 732", "elementId": "lever_base"}, {"d": "M646 720 L587 737", "elementId": "lever_base"}, {"d": "M606 753 L545 771", "elementId": "lever_base"}, {"d": "M536 774 L483 788", "elementId": "lever_base"}, {"d": "M538 778 L496 793 L469 794", "elementId": "lever_base"}, {"d": "M564 741 L437 778", "elementId": "lever_base"}, {"d": "M528 709 L434 736", "elementId": "lever_base"}, {"d": "M412 742 L373 752", "elementId": "lever_base"}, {"d": "M376 758 L406 756 L372 767 L369 760", "elementId": "lever_base"}, {"d": "M367 758 L301 776", "elementId": "lever_base"}, {"d": "M368 753 L280 778", "elementId": "lever_base"}, {"d": "M303 787 L275 789", "elementId": "lever_base"}, {"d": "M304 789 L273 796", "elementId": "lever_base"}, {"d": "M270 780 L242 788", "elementId": "lever_base"}, {"d": "M268 784 L242 792", "elementId": "lever_base"}, {"d": "M239 798 L201 809", "elementId": "lever_base"}, {"d": "M194 806 L169 812", "elementId": "lever_base"}, {"d": "M176 859 L151 864", "elementId": "lever_base"}, {"d": "M149 881 L181 882", "elementId": "lever_base"}, {"d": "M261 843 L236 851", "elementId": "lever_base"}, {"d": "M365 820 L312 837", "elementId": "lever_base"}, {"d": "M386 820 L296 848", "elementId": "lever_base"}, {"d": "M861 765 L857 768", "elementId": "lever_base"}, {"d": "M923 758 L915 768", "elementId": "lever_base"}, {"d": "M926 760 L930 768", "elementId": "lever_base"}, {"d": "M917 771 L927 772", "elementId": "lever_base"}, {"d": "M929 773 L934 791", "elementId": "lever_base"}, {"d": "M931 770 L952 776", "elementId": "lever_base"}, {"d": "M954 779 L953 786", "elementId": "lever_base"}, {"d": "M956 778 L967 783", "elementId": "lever_base"}, {"d": "M965 755 L956 775", "elementId": "lever_base"}, {"d": "M971 754 L981 777", "elementId": "lever_base"}, {"d": "M980 781 L974 783", "elementId": "lever_base"}, {"d": "M974 787 L981 791", "elementId": "lever_base"}, {"d": "M983 781 L984 789", "elementId": "lever_base"}, {"d": "M985 794 L986 798", "elementId": "lever_base"}, {"d": "M986 792 L1003 798", "elementId": "lever_base"}, {"d": "M991 804 L994 808", "elementId": "lever_base"}, {"d": "M986 806 L985 813", "elementId": "lever_base"}, {"d": "M994 813 L989 816", "elementId": "lever_base"}, {"d": "M1003 802 L998 808", "elementId": "lever_base"}, {"d": "M1008 801 L1027 815", "elementId": "lever_base"}, {"d": "M1033 804 L1030 822", "elementId": "lever_base"}, {"d": "M1029 824 L1021 837", "elementId": "lever_base"}, {"d": "M1031 824 L1023 841", "elementId": "lever_base"}, {"d": "M1018 839 L1010 840", "elementId": "lever_base"}, {"d": "M982 837 L1005 843", "elementId": "lever_base"}, {"d": "M982 825 L981 834", "elementId": "lever_base"}, {"d": "M980 823 L971 828", "elementId": "lever_base"}, {"d": "M971 831 L977 835", "elementId": "lever_base"}, {"d": "M964 831 L956 836", "elementId": "lever_base"}, {"d": "M957 824 L964 828", "elementId": "lever_base"}, {"d": "M951 826 L953 835", "elementId": "lever_base"}, {"d": "M938 821 L948 823", "elementId": "lever_base"}, {"d": "M942 810 L937 818", "elementId": "lever_base"}, {"d": "M948 813 L950 817", "elementId": "lever_base"}, {"d": "M948 805 L948 809", "elementId": "lever_base"}, {"d": "M949 798 L947 803", "elementId": "lever_base"}, {"d": "M937 795 L942 805", "elementId": "lever_base"}, {"d": "M949 790 L938 792", "elementId": "lever_base"}, {"d": "M957 793 L952 796", "elementId": "lever_base"}, {"d": "M934 822 L927 837", "elementId": "lever_base"}, {"d": "M925 839 L917 841", "elementId": "lever_base"}, {"d": "M915 844 L922 854", "elementId": "lever_base"}, {"d": "M929 845 L925 853", "elementId": "lever_base"}, {"d": "M924 856 L937 866", "elementId": "lever_base"}, {"d": "M929 858 L938 864", "elementId": "lever_base"}, {"d": "M949 870 L956 871", "elementId": "lever_base"}, {"d": "M962 863 L958 869", "elementId": "lever_base"}, {"d": "M958 873 L972 873", "elementId": "lever_base"}, {"d": "M970 864 L973 869", "elementId": "lever_base"}, {"d": "M986 869 L982 870", "elementId": "lever_base"}, {"d": "M997 864 L992 867", "elementId": "lever_base"}, {"d": "M1011 857 L1004 860", "elementId": "lever_base"}, {"d": "M979 838 L970 860", "elementId": "lever_base"}, {"d": "M955 840 L963 860", "elementId": "lever_base"}, {"d": "M952 838 L931 843", "elementId": "lever_base"}, {"d": "M1006 773 L984 779", "elementId": "lever_base"}, {"d": "M1008 775 L1012 779", "elementId": "lever_base"}, {"d": "M1022 777 L1016 780", "elementId": "lever_base"}, {"d": "M1019 766 L1024 773", "elementId": "lever_base"}, {"d": "M1016 765 L1009 771", "elementId": "lever_base"}, {"d": "M1000 747 L1018 763", "elementId": "lever_base"}, {"d": "M977 742 L981 742", "elementId": "lever_base"}, {"d": "M975 745 L971 752", "elementId": "lever_base"}, {"d": "M957 739 L941 744", "elementId": "lever_base"}, {"d": "M954 743 L942 746", "elementId": "lever_base"}, {"d": "M1014 782 L1007 798", "elementId": "lever_base"}, {"d": "M1026 781 L1029 788", "elementId": "lever_base"}, {"d": "M1025 776 L1031 788", "elementId": "lever_base"}, {"d": "M1063 754 L1077 777", "elementId": "lever_base"}, {"d": "M1059 747 L1061 751", "elementId": "lever_base"}, {"d": "M1052 722 L1050 727", "elementId": "lever_base"}, {"d": "M1083 790 L1085 796", "elementId": "lever_base"}, {"d": "M1090 803 L1092 807", "elementId": "lever_base"}, {"d": "M1094 810 L1096 814", "elementId": "lever_base"}, {"d": "M1100 807 L1102 811", "elementId": "lever_base"}, {"d": "M1098 817 L1099 822", "elementId": "lever_base"}, {"d": "M1128 874 L1133 877", "elementId": "lever_base"}, {"d": "M1144 912 L1143 916", "elementId": "lever_base"}, {"d": "M1150 926 L1148 932", "elementId": "lever_base"}, {"d": "M1148 934 L1158 934", "elementId": "lever_base"}, {"d": "M1156 923 L1160 932", "elementId": "lever_base"}, {"d": "M1154 905 L1165 920", "elementId": "lever_base"}, {"d": "M1164 936 L1181 937", "elementId": "lever_base"}, {"d": "M1146 933 L1127 935", "elementId": "lever_base"}, {"d": "M1049 933 L1056 935", "elementId": "lever_base"}, {"d": "M1003 933 L1007 933", "elementId": "lever_base"}, {"d": "M994 944 L985 945", "elementId": "lever_base"}, {"d": "M944 930 L949 930", "elementId": "lever_base"}, {"d": "M901 941 L905 941", "elementId": "lever_base"}, {"d": "M905 936 L880 938", "elementId": "lever_base"}, {"d": "M880 945 L902 946", "elementId": "lever_base"}, {"d": "M871 941 L876 945", "elementId": "lever_base"}, {"d": "M871 938 L876 938", "elementId": "lever_base"}, {"d": "M854 938 L863 938", "elementId": "lever_base"}, {"d": "M863 940 L854 945", "elementId": "lever_base"}, {"d": "M846 939 L841 940", "elementId": "lever_base"}, {"d": "M841 934 L846 937", "elementId": "lever_base"}, {"d": "M827 943 L850 945", "elementId": "lever_base"}, {"d": "M831 933 L810 934", "elementId": "lever_base"}, {"d": "M806 932 L790 933", "elementId": "lever_base"}, {"d": "M804 936 L792 937", "elementId": "lever_base"}, {"d": "M795 943 L779 944", "elementId": "lever_base"}, {"d": "M781 942 L788 942", "elementId": "lever_base"}, {"d": "M786 933 L781 934", "elementId": "lever_base"}, {"d": "M775 928 L779 936", "elementId": "lever_base"}, {"d": "M780 923 L777 926", "elementId": "lever_base"}, {"d": "M778 917 L774 921", "elementId": "lever_base"}, {"d": "M771 924 L768 931", "elementId": "lever_base"}, {"d": "M769 934 L772 940", "elementId": "lever_base"}, {"d": "M758 943 L770 943", "elementId": "lever_base"}, {"d": "M786 903 L783 909", "elementId": "lever_base"}, {"d": "M720 718 L713 720", "elementId": "lever_base"}, {"d": "M710 721 L699 724", "elementId": "lever_base"}, {"d": "M695 718 L697 723", "elementId": "lever_base"}, {"d": "M661 728 L663 732", "elementId": "lever_base"}, {"d": "M663 735 L659 736", "elementId": "lever_base"}, {"d": "M651 732 L651 737", "elementId": "lever_base"}, {"d": "M647 733 L648 738", "elementId": "lever_base"}, {"d": "M645 731 L631 735", "elementId": "lever_base"}, {"d": "M648 740 L633 745", "elementId": "lever_base"}, {"d": "M631 738 L631 743", "elementId": "lever_base"}, {"d": "M625 740 L627 744", "elementId": "lever_base"}, {"d": "M626 747 L618 749", "elementId": "lever_base"}, {"d": "M622 738 L612 743", "elementId": "lever_base"}, {"d": "M610 743 L588 746", "elementId": "lever_base"}, {"d": "M582 741 L584 745", "elementId": "lever_base"}, {"d": "M585 748 L580 749", "elementId": "lever_base"}, {"d": "M578 750 L573 751", "elementId": "lever_base"}, {"d": "M570 752 L566 753", "elementId": "lever_base"}, {"d": "M564 747 L564 751", "elementId": "lever_base"}, {"d": "M537 753 L533 754", "elementId": "lever_base"}, {"d": "M539 761 L535 762", "elementId": "lever_base"}, {"d": "M532 763 L522 766", "elementId": "lever_base"}, {"d": "M530 755 L519 758", "elementId": "lever_base"}, {"d": "M516 759 L502 763", "elementId": "lever_base"}, {"d": "M519 767 L505 771", "elementId": "lever_base"}, {"d": "M502 772 L497 773", "elementId": "lever_base"}, {"d": "M495 767 L495 771", "elementId": "lever_base"}, {"d": "M499 764 L495 765", "elementId": "lever_base"}, {"d": "M489 767 L482 773", "elementId": "lever_base"}, {"d": "M492 775 L482 776", "elementId": "lever_base"}, {"d": "M476 779 L480 786", "elementId": "lever_base"}, {"d": "M470 781 L473 788", "elementId": "lever_base"}, {"d": "M468 780 L460 786", "elementId": "lever_base"}, {"d": "M480 789 L475 790", "elementId": "lever_base"}, {"d": "M457 788 L438 791", "elementId": "lever_base"}, {"d": "M436 781 L436 789", "elementId": "lever_base"}, {"d": "M434 779 L434 790", "elementId": "lever_base"}, {"d": "M434 792 L422 795", "elementId": "lever_base"}, {"d": "M409 794 L419 794", "elementId": "lever_base"}, {"d": "M419 797 L410 807", "elementId": "lever_base"}, {"d": "M408 797 L408 805", "elementId": "lever_base"}, {"d": "M403 798 L403 806", "elementId": "lever_base"}, {"d": "M400 799 L400 807", "elementId": "lever_base"}, {"d": "M396 800 L396 808", "elementId": "lever_base"}, {"d": "M393 801 L394 809", "elementId": "lever_base"}, {"d": "M391 799 L385 800", "elementId": "lever_base"}, {"d": "M384 815 L367 819", "elementId": "lever_base"}, {"d": "M362 812 L365 818", "elementId": "lever_base"}, {"d": "M367 807 L363 810", "elementId": "lever_base"}, {"d": "M351 813 L346 816", "elementId": "lever_base"}, {"d": "M348 808 L342 810", "elementId": "lever_base"}, {"d": "M330 815 L331 819", "elementId": "lever_base"}, {"d": "M327 816 L327 820", "elementId": "lever_base"}, {"d": "M323 824 L317 826", "elementId": "lever_base"}, {"d": "M319 817 L314 818", "elementId": "lever_base"}, {"d": "M308 822 L308 826", "elementId": "lever_base"}, {"d": "M304 823 L305 828", "elementId": "lever_base"}, {"d": "M300 824 L301 829", "elementId": "lever_base"}, {"d": "M296 826 L296 831", "elementId": "lever_base"}, {"d": "M291 827 L292 832", "elementId": "lever_base"}, {"d": "M295 836 L295 840", "elementId": "lever_base"}, {"d": "M281 837 L285 837", "elementId": "lever_base"}, {"d": "M278 831 L279 835", "elementId": "lever_base"}, {"d": "M275 832 L275 840", "elementId": "lever_base"}, {"d": "M273 830 L264 841", "elementId": "lever_base"}, {"d": "M274 843 L264 844", "elementId": "lever_base"}, {"d": "M309 831 L310 835", "elementId": "lever_base"}, {"d": "M305 787 L309 787", "elementId": "lever_base"}, {"d": "M291 751 L279 775", "elementId": "lever_base"}, {"d": "M275 783 L274 787", "elementId": "lever_base"}, {"d": "M271 790 L269 794", "elementId": "lever_base"}, {"d": "M270 798 L254 803", "elementId": "lever_base"}, {"d": "M216 798 L200 803", "elementId": "lever_base"}, {"d": "M162 810 L166 811", "elementId": "lever_base"}, {"d": "M158 818 L152 820", "elementId": "lever_base"}, {"d": "M154 813 L150 815", "elementId": "lever_base"}, {"d": "M135 816 L131 823", "elementId": "lever_base"}, {"d": "M140 825 L134 831", "elementId": "lever_base"}, {"d": "M134 834 L131 847", "elementId": "lever_base"}, {"d": "M128 839 L128 847", "elementId": "lever_base"}, {"d": "M127 837 L120 839 L120 853", "elementId": "lever_base"}, {"d": "M130 855 L134 860", "elementId": "lever_base"}, {"d": "M137 862 L148 864", "elementId": "lever_base"}, {"d": "M148 870 L147 876", "elementId": "lever_base"}, {"d": "M154 876 L149 878", "elementId": "lever_base"}, {"d": "M168 873 L157 875", "elementId": "lever_base"}, {"d": "M155 868 L168 870", "elementId": "lever_base"}, {"d": "M176 861 L171 870", "elementId": "lever_base"}, {"d": "M181 861 L185 862", "elementId": "lever_base"}, {"d": "M187 864 L191 869", "elementId": "lever_base"}, {"d": "M192 872 L171 873", "elementId": "lever_base"}, {"d": "M208 868 L201 870", "elementId": "lever_base"}, {"d": "M208 861 L208 866", "elementId": "lever_base"}, {"d": "M217 866 L210 867", "elementId": "lever_base"}, {"d": "M213 857 L217 863", "elementId": "lever_base"}, {"d": "M203 850 L211 852", "elementId": "lever_base"}, {"d": "M198 854 L198 858", "elementId": "lever_base"}, {"d": "M196 852 L192 853", "elementId": "lever_base"}, {"d": "M234 850 L218 851", "elementId": "lever_base"}, {"d": "M231 859 L225 862", "elementId": "lever_base"}, {"d": "M134 869 L137 875", "elementId": "lever_base"}, {"d": "M130 869 L133 879", "elementId": "lever_base"}, {"d": "M411 746 L404 748", "elementId": "lever_base"}, {"d": "M419 740 L415 741", "elementId": "lever_base"}, {"d": "M654 720 L655 724", "elementId": "lever_base"}, {"d": "M230 645 L221 673 L225 690 L238 676 L234 663", "elementId": "lever_arm"}, {"d": "M233 499 L231 522 L240 543", "elementId": "lever_arm"}, {"d": "M234 645 L232 656", "elementId": "lever_arm"}, {"d": "M281 585 L235 634", "elementId": "lever_arm"}, {"d": "M236 508 L244 540", "elementId": "lever_arm"}, {"d": "M238 499 L238 504", "elementId": "lever_arm"}, {"d": "M251 467 L239 495", "elementId": "lever_arm"}, {"d": "M239 507 L243 515", "elementId": "lever_arm"}, {"d": "M248 544 L252 549", "elementId": "lever_arm"}, {"d": "M287 436 L256 455", "elementId": "lever_arm"}, {"d": "M257 555 L266 561", "elementId": "lever_arm"}, {"d": "M302 438 L261 458", "elementId": "lever_arm"}, {"d": "M268 564 L271 567", "elementId": "lever_arm"}, {"d": "M273 623 L273 649", "elementId": "lever_arm"}, {"d": "M275 615 L274 620", "elementId": "lever_arm"}, {"d": "M276 657 L288 685", "elementId": "lever_arm"}, {"d": "M278 625 L277 647", "elementId": "lever_arm"}, {"d": "M283 587 L278 606", "elementId": "lever_arm"}, {"d": "M279 617 L279 621", "elementId": "lever_arm"}, {"d": "M286 570 L281 572", "elementId": "lever_arm"}, {"d": "M284 599 L282 607", "elementId": "lever_arm"}, {"d": "M289 573 L283 583", "elementId": "lever_arm"}, {"d": "M291 685 L292 690", "elementId": "lever_arm"}, {"d": "M293 693 L297 739", "elementId": "lever_arm"}, {"d": "M294 574 L300 574", "elementId": "lever_arm"}, {"d": "M296 572 L300 572", "elementId": "lever_arm"}, {"d": "M382 522 L355 559 L302 573", "elementId": "lever_arm"}, {"d": "M329 682 L304 688", "elementId": "lever_arm"}, {"d": "M306 436 L341 434 L364 453", "elementId": "lever_arm"}, {"d": "M307 439 L327 439", "elementId": "lever_arm"}, {"d": "M359 510 L343 526 L319 519", "elementId": "lever_arm"}, {"d": "M336 441 L362 454", "elementId": "lever_arm"}, {"d": "M344 572 L347 577", "elementId": "lever_arm"}, {"d": "M352 664 L344 678", "elementId": "lever_arm"}, {"d": "M344 681 L380 706 L372 750", "elementId": "lever_arm"}, {"d": "M350 589 L352 596", "elementId": "lever_arm"}, {"d": "M354 605 L357 622", "elementId": "lever_arm"}, {"d": "M357 664 L355 673", "elementId": "lever_arm"}, {"d": "M356 482 L359 489", "elementId": "lever_arm"}, {"d": "M356 625 L356 629", "elementId": "lever_arm"}, {"d": "M357 641 L356 654", "elementId": "lever_arm"}, {"d": "M357 588 L394 622 L412 630 L433 628 L441 638 L419 643 L411 636", "elementId": "lever_arm"}, {"d": "M357 657 L358 661", "elementId": "lever_arm"}, {"d": "M359 625 L360 629", "elementId": "lever_arm"}, {"d": "M369 461 L373 465", "elementId": "lever_arm"}, {"d": "M375 470 L381 483", "elementId": "lever_arm"}, {"d": "M378 467 L391 488", "elementId": "lever_arm"}, {"d": "M385 509 L383 518", "elementId": "lever_arm"}, {"d": "M384 500 L384 505", "elementId": "lever_arm"}, {"d": "M385 492 L387 496", "elementId": "lever_arm"}, {"d": "M637 673 L541 701", "elementId": "lever_arm"}, {"d": "M564 701 L541 706", "elementId": "lever_arm"}, {"d": "M589 694 L577 697", "elementId": "lever_arm"}, {"d": "M598 692 L604 692", "elementId": "lever_arm"}, {"d": "M603 688 L599 689", "elementId": "lever_arm"}, {"d": "M638 677 L626 681", "elementId": "lever_arm"}, {"d": "M638 682 L627 685", "elementId": "lever_arm"}, {"d": "M646 669 L640 671", "elementId": "lever_arm"}, {"d": "M648 673 L642 675", "elementId": "lever_arm"}, {"d": "M654 677 L642 681", "elementId": "lever_arm"}, {"d": "M732 652 L657 676", "elementId": "lever_arm"}, {"d": "M666 715 L661 716", "elementId": "lever_arm"}, {"d": "M675 712 L679 713", "elementId": "lever_arm"}, {"d": "M696 708 L687 713", "elementId": "lever_arm"}, {"d": "M687 715 L693 716", "elementId": "lever_arm"}, {"d": "M714 651 L691 657", "elementId": "lever_arm"}, {"d": "M706 709 L700 710", "elementId": "lever_arm"}, {"d": "M709 707 L713 707", "elementId": "lever_arm"}, {"d": "M709 710 L711 718", "elementId": "lever_arm"}, {"d": "M721 705 L715 706", "elementId": "lever_arm"}, {"d": "M715 708 L720 716", "elementId": "lever_arm"}, {"d": "M739 700 L723 704", "elementId": "lever_arm"}, {"d": "M723 706 L723 714", "elementId": "lever_arm"}, {"d": "M725 648 L730 648", "elementId": "lever_arm"}, {"d": "M745 710 L725 716", "elementId": "lever_arm"}, {"d": "M733 646 L739 646", "elementId": "lever_arm"}, {"d": "M739 650 L734 651", "elementId": "lever_arm"}, {"d": "M743 637 L737 639", "elementId": "lever_arm"}, {"d": "M742 698 L748 698", "elementId": "lever_arm"}, {"d": "M750 699 L750 706", "elementId": "lever_arm"}, {"d": "M827 620 L751 643", "elementId": "lever_arm"}, {"d": "M753 698 L753 705", "elementId": "lever_arm"}, {"d": "M757 697 L757 704", "elementId": "lever_arm"}, {"d": "M760 696 L760 703", "elementId": "lever_arm"}, {"d": "M764 695 L764 702", "elementId": "lever_arm"}, {"d": "M767 695 L767 701", "elementId": "lever_arm"}, {"d": "M771 693 L771 700", "elementId": "lever_arm"}, {"d": "M788 688 L776 689", "elementId": "lever_arm"}, {"d": "M784 697 L778 701", "elementId": "lever_arm"}, {"d": "M786 621 L781 623", "elementId": "lever_arm"}, {"d": "M810 681 L791 687", "elementId": "lever_arm"}, {"d": "M810 685 L795 695", "elementId": "lever_arm"}, {"d": "M826 609 L822 610", "elementId": "lever_arm"}, {"d": "M826 674 L831 674", "elementId": "lever_arm"}, {"d": "M835 619 L831 620", "elementId": "lever_arm"}, {"d": "M833 676 L833 684", "elementId": "lever_arm"}, {"d": "M844 672 L834 673", "elementId": "lever_arm"}, {"d": "M846 674 L835 686", "elementId": "lever_arm"}, {"d": "M842 605 L838 606", "elementId": "lever_arm"}, {"d": "M858 670 L848 672", "elementId": "lever_arm"}, {"d": "M902 595 L852 610", "elementId": "lever_arm"}, {"d": "M905 600 L852 614", "elementId": "lever_arm"}, {"d": "M864 663 L860 668", "elementId": "lever_arm"}, {"d": "M872 675 L866 676", "elementId": "lever_arm"}, {"d": "M871 656 L867 659", "elementId": "lever_arm"}, {"d": "M870 667 L873 672", "elementId": "lever_arm"}, {"d": "M878 666 L879 671", "elementId": "lever_arm"}, {"d": "M882 666 L883 670", "elementId": "lever_arm"}, {"d": "M885 664 L886 669", "elementId": "lever_arm"}, {"d": "M886 654 L886 658", "elementId": "lever_arm"}, {"d": "M893 659 L888 660", "elementId": "lever_arm"}, {"d": "M916 665 L888 671", "elementId": "lever_arm"}, {"d": "M891 652 L893 656", "elementId": "lever_arm"}, {"d": "M898 701 L897 705", "elementId": "lever_arm"}, {"d": "M903 690 L900 694", "elementId": "lever_arm"}, {"d": "M917 667 L905 688", "elementId": "lever_arm"}, {"d": "M908 654 L920 654", "elementId": "lever_arm"}, {"d": "M917 591 L913 592", "elementId": "lever_arm"}, {"d": "M920 595 L914 597", "elementId": "lever_arm"}, {"d": "M921 657 L918 665", "elementId": "lever_arm"}, {"d": "M934 625 L928 632", "elementId": "lever_arm"}, {"d": "M933 646 L929 648", "elementId": "lever_arm"}, {"d": "M936 645 L940 645", "elementId": "lever_arm"}, {"d": "M939 636 L942 644", "elementId": "lever_arm"}, {"d": "M948 656 L966 662", "elementId": "lever_arm"}, {"d": "M955 610 L949 614", "elementId": "lever_arm"}, {"d": "M1113 534 L952 581", "elementId": "lever_arm"}, {"d": "M973 581 L953 586", "elementId": "lever_arm"}, {"d": "M965 606 L957 608", "elementId": "lever_arm"}, {"d": "M961 612 L965 612", "elementId": "lever_arm"}, {"d": "M967 603 L990 608", "elementId": "lever_arm"}, {"d": "M974 613 L978 613", "elementId": "lever_arm"}, {"d": "M976 606 L982 609", "elementId": "lever_arm"}, {"d": "M1092 546 L982 578", "elementId": "lever_arm"}, {"d": "M991 580 L983 582", "elementId": "lever_arm"}, {"d": "M991 627 L994 631", "elementId": "lever_arm"}, {"d": "M1094 550 L994 580", "elementId": "lever_arm"}, {"d": "M1017 614 L997 620", "elementId": "lever_arm"}, {"d": "M997 622 L998 628", "elementId": "lever_arm"}, {"d": "M998 654 L1012 676", "elementId": "lever_arm"}, {"d": "M1002 641 L1004 647", "elementId": "lever_arm"}, {"d": "M1013 636 L1004 638", "elementId": "lever_arm"}, {"d": "M1006 650 L1017 675", "elementId": "lever_arm"}, {"d": "M1022 623 L1007 628", "elementId": "lever_arm"}, {"d": "M1007 647 L1011 647", "elementId": "lever_arm"}, {"d": "M1012 649 L1031 683", "elementId": "lever_arm"}, {"d": "M1018 678 L1024 689", "elementId": "lever_arm"}, {"d": "M1019 616 L1021 620", "elementId": "lever_arm"}, {"d": "M1038 628 L1021 633", "elementId": "lever_arm"}, {"d": "M1023 615 L1023 619", "elementId": "lever_arm"}, {"d": "M1045 631 L1024 636", "elementId": "lever_arm"}, {"d": "M1026 692 L1042 721", "elementId": "lever_arm"}, {"d": "M1027 614 L1028 618", "elementId": "lever_arm"}, {"d": "M1032 613 L1032 617", "elementId": "lever_arm"}, {"d": "M1032 685 L1049 716", "elementId": "lever_arm"}, {"d": "M1042 607 L1035 609", "elementId": "lever_arm"}, {"d": "M1035 612 L1036 616", "elementId": "lever_arm"}, {"d": "M1037 620 L1038 625", "elementId": "lever_arm"}, {"d": "M1047 616 L1038 618", "elementId": "lever_arm"}, {"d": "M1046 626 L1041 627", "elementId": "lever_arm"}, {"d": "M1044 609 L1047 613", "elementId": "lever_arm"}, {"d": "M1048 608 L1049 612", "elementId": "lever_arm"}, {"d": "M1057 603 L1049 605", "elementId": "lever_arm"}, {"d": "M1058 612 L1051 614", "elementId": "lever_arm"}, {"d": "M1070 599 L1059 602", "elementId": "lever_arm"}, {"d": "M1059 604 L1059 609", "elementId": "lever_arm"}, {"d": "M1076 618 L1060 623", "elementId": "lever_arm"}, {"d": "M1073 609 L1061 611", "elementId": "lever_arm"}, {"d": "M1072 601 L1074 606", "elementId": "lever_arm"}, {"d": "M1086 595 L1073 598", "elementId": "lever_arm"}, {"d": "M1075 611 L1076 615", "elementId": "lever_arm"}, {"d": "M1079 606 L1087 606", "elementId": "lever_arm"}, {"d": "M1087 613 L1083 615", "elementId": "lever_arm"}, {"d": "M1088 597 L1092 605", "elementId": "lever_arm"}, {"d": "M1095 593 L1089 594", "elementId": "lever_arm"}, {"d": "M1099 604 L1095 606", "elementId": "lever_arm"}, {"d": "M1098 598 L1099 602", "elementId": "lever_arm"}, {"d": "M1112 590 L1099 594", "elementId": "lever_arm"}, {"d": "M1113 602 L1101 603", "elementId": "lever_arm"}, {"d": "M1104 541 L1108 541", "elementId": "lever_arm"}, {"d": "M1115 595 L1115 599", "elementId": "lever_arm"}, {"d": "M1157 597 L1117 602", "elementId": "lever_arm"}, {"d": "M1124 593 L1130 594", "elementId": "lever_arm"}, {"d": "M1229 505 L1128 535", "elementId": "lever_arm"}, {"d": "M1132 585 L1132 592", "elementId": "lever_arm"}, {"d": "M1136 580 L1133 581", "elementId": "lever_arm"}, {"d": "M1138 593 L1134 594", "elementId": "lever_arm"}, {"d": "M1135 585 L1136 589", "elementId": "lever_arm"}, {"d": "M1138 584 L1138 588", "elementId": "lever_arm"}, {"d": "M1151 574 L1154 574", "elementId": "lever_arm"}, {"d": "M1157 584 L1153 587", "elementId": "lever_arm"}, {"d": "M1158 570 L1157 573", "elementId": "lever_arm"}, {"d": "M1166 573 L1162 574", "elementId": "lever_arm"}, {"d": "M1170 593 L1162 595", "elementId": "lever_arm"}, {"d": "M1164 568 L1167 570", "elementId": "lever_arm"}, {"d": "M1170 586 L1171 590", "elementId": "lever_arm"}, {"d": "M1174 585 L1174 589", "elementId": "lever_arm"}, {"d": "M1177 572 L1182 578", "elementId": "lever_arm"}, {"d": "M1187 567 L1178 569", "elementId": "lever_arm"}, {"d": "M1178 584 L1178 588", "elementId": "lever_arm"}, {"d": "M1184 588 L1180 590", "elementId": "lever_arm"}, {"d": "M1187 571 L1187 576", "elementId": "lever_arm"}, {"d": "M1191 585 L1187 587", "elementId": "lever_arm"}, {"d": "M1211 575 L1199 580", "elementId": "lever_arm"}, {"d": "M1209 562 L1201 563", "elementId": "lever_arm"}, {"d": "M1205 573 L1210 573", "elementId": "lever_arm"}, {"d": "M1224 560 L1213 561", "elementId": "lever_arm"}, {"d": "M1223 564 L1219 568", "elementId": "lever_arm"}, {"d": "M1219 574 L1224 574", "elementId": "lever_arm"}, {"d": "M1225 566 L1225 571", "elementId": "lever_arm"}, {"d": "M1228 563 L1228 571", "elementId": "lever_arm"}, {"d": "M1274 547 L1229 559", "elementId": "lever_arm"}, {"d": "M1276 560 L1236 571", "elementId": "lever_arm"}, {"d": "M1264 492 L1248 496", "elementId": "lever_arm"}, {"d": "M1267 496 L1250 502", "elementId": "lever_arm"}, {"d": "M1257 395 L1254 400", "elementId": "lever_arm"}, {"d": "M1254 410 L1257 423", "elementId": "lever_arm"}, {"d": "M1257 469 L1259 472", "elementId": "lever_arm"}, {"d": "M1260 414 L1260 420", "elementId": "lever_arm"}, {"d": "M1266 461 L1261 470", "elementId": "lever_arm"}, {"d": "M1290 505 L1261 510", "elementId": "lever_arm"}, {"d": "M1262 425 L1267 428", "elementId": "lever_arm"}, {"d": "M1263 483 L1265 489", "elementId": "lever_arm"}, {"d": "M1266 479 L1273 481", "elementId": "lever_arm"}, {"d": "M1274 484 L1274 494", "elementId": "lever_arm"}, {"d": "M1274 497 L1282 498", "elementId": "lever_arm"}, {"d": "M1276 482 L1281 483", "elementId": "lever_arm"}, {"d": "M1276 549 L1276 558", "elementId": "lever_arm"}, {"d": "M1282 558 L1278 559", "elementId": "lever_arm"}, {"d": "M1280 547 L1282 555", "elementId": "lever_arm"}, {"d": "M1283 485 L1284 496", "elementId": "lever_arm"}, {"d": "M1285 499 L1292 500", "elementId": "lever_arm"}, {"d": "M1285 546 L1285 554", "elementId": "lever_arm"}, {"d": "M1308 541 L1291 542", "elementId": "lever_arm"}, {"d": "M1296 554 L1292 555", "elementId": "lever_arm"}, {"d": "M1308 543 L1298 552", "elementId": "lever_arm"}, {"d": "M1332 535 L1310 542", "elementId": "lever_arm"}, {"d": "M1344 527 L1335 533", "elementId": "lever_arm"}, {"d": "M1335 536 L1339 538", "elementId": "lever_arm"}, {"d": "M1342 540 L1347 540", "elementId": "lever_arm"}, {"d": "M1355 524 L1346 526", "elementId": "lever_arm"}, {"d": "M1372 533 L1353 538", "elementId": "lever_arm"}, {"d": "M1365 515 L1365 519", "elementId": "lever_arm"}, {"d": "M1369 513 L1369 518", "elementId": "lever_arm"}, {"d": "M1370 523 L1372 531", "elementId": "lever_arm"}, {"d": "M1382 518 L1372 519", "elementId": "lever_arm"}, {"d": "M1372 521 L1375 529", "elementId": "lever_arm"}, {"d": "M1386 529 L1377 531", "elementId": "lever_arm"}, {"d": "M1385 516 L1390 516", "elementId": "lever_arm"}, {"d": "M1392 517 L1393 524", "elementId": "lever_arm"}, {"d": "M1396 516 L1396 523", "elementId": "lever_arm"}, {"d": "M1399 515 L1400 521", "elementId": "lever_arm"}, {"d": "M1402 514 L1402 520", "elementId": "lever_arm"}, {"d": "M1406 515 L1406 520", "elementId": "lever_arm"}, {"d": "M1412 521 L1408 522", "elementId": "lever_arm"}, {"d": "M1425 506 L1421 513", "elementId": "lever_arm"}, {"d": "M1448 513 L1424 518", "elementId": "lever_arm"}, {"d": "M1455 510 L1451 511", "elementId": "lever_arm"}, {"d": "M1425 503 L1413 508", "elementId": "wealth_assets"}, {"d": "M1298 500 L1307 500", "elementId": "wealth_assets"}, {"d": "M1501 499 L1480 504", "elementId": "wealth_assets"}, {"d": "M1320 498 L1311 500", "elementId": "wealth_assets"}, {"d": "M1334 496 L1324 498", "elementId": "wealth_assets"}, {"d": "M1460 495 L1428 504", "elementId": "wealth_assets"}, {"d": "M1466 493 L1462 494", "elementId": "wealth_assets"}, {"d": "M1347 492 L1337 495", "elementId": "wealth_assets"}, {"d": "M1479 489 L1468 492", "elementId": "wealth_assets"}, {"d": "M1539 488 L1505 497", "elementId": "wealth_assets"}, {"d": "M1359 487 L1350 490", "elementId": "wealth_assets"}, {"d": "M1455 487 L1460 493", "elementId": "wealth_assets"}, {"d": "M1496 487 L1503 496", "elementId": "wealth_assets"}, {"d": "M1294 486 L1296 498", "elementId": "wealth_assets"}, {"d": "M1493 486 L1481 488", "elementId": "wealth_assets"}, {"d": "M1307 485 L1309 498", "elementId": "wealth_assets"}, {"d": "M1321 485 L1322 496", "elementId": "wealth_assets"}, {"d": "M1453 485 L1369 511", "elementId": "wealth_assets"}, {"d": "M1465 484 L1466 491", "elementId": "wealth_assets"}, {"d": "M1285 483 L1292 484", "elementId": "wealth_assets"}, {"d": "M1305 483 L1296 484", "elementId": "wealth_assets"}, {"d": "M1309 483 L1319 483", "elementId": "wealth_assets"}, {"d": "M1463 483 L1456 484", "elementId": "wealth_assets"}, {"d": "M1333 482 L1335 493", "elementId": "wealth_assets"}, {"d": "M1331 481 L1322 482", "elementId": "wealth_assets"}, {"d": "M1368 481 L1362 485", "elementId": "wealth_assets"}, {"d": "M1470 481 L1465 482", "elementId": "wealth_assets"}, {"d": "M1346 479 L1347 489", "elementId": "wealth_assets"}, {"d": "M1476 479 L1479 485", "elementId": "wealth_assets"}, {"d": "M1344 477 L1335 479", "elementId": "wealth_assets"}, {"d": "M1539 477 L1539 486", "elementId": "wealth_assets"}, {"d": "M1555 477 L1547 485", "elementId": "wealth_assets"}, {"d": "M1542 476 L1542 484", "elementId": "wealth_assets"}, {"d": "M1537 475 L1496 484", "elementId": "wealth_assets"}, {"d": "M1545 475 L1545 483", "elementId": "wealth_assets"}, {"d": "M1358 473 L1359 484", "elementId": "wealth_assets"}, {"d": "M1356 472 L1347 475", "elementId": "wealth_assets"}, {"d": "M1555 471 L1546 472", "elementId": "wealth_assets"}, {"d": "M1366 469 L1367 478", "elementId": "wealth_assets"}, {"d": "M1393 469 L1418 472", "elementId": "wealth_assets"}, {"d": "M1363 468 L1358 471", "elementId": "wealth_assets"}, {"d": "M1434 468 L1428 469", "elementId": "wealth_assets"}, {"d": "M1304 467 L1312 467", "elementId": "wealth_assets"}, {"d": "M1450 467 L1438 468", "elementId": "wealth_assets"}, {"d": "M1578 467 L1571 477 L1559 474", "elementId": "wealth_assets"}, {"d": "M1407 466 L1414 466", "elementId": "wealth_assets"}, {"d": "M1605 466 L1594 469", "elementId": "wealth_assets"}, {"d": "M1373 465 L1370 479", "elementId": "wealth_assets"}, {"d": "M1398 464 L1404 465", "elementId": "wealth_assets"}, {"d": "M1371 463 L1366 466", "elementId": "wealth_assets"}, {"d": "M1466 463 L1453 466", "elementId": "wealth_assets"}, {"d": "M1580 465 L1557 469", "elementId": "wealth_assets"}, {"d": "M1311 462 L1306 463", "elementId": "wealth_assets"}, {"d": "M1325 460 L1322 464", "elementId": "wealth_assets"}, {"d": "M1349 460 L1316 473", "elementId": "wealth_assets"}, {"d": "M1387 459 L1375 462", "elementId": "wealth_assets"}, {"d": "M1390 459 L1395 462", "elementId": "wealth_assets"}, {"d": "M1479 459 L1469 462", "elementId": "wealth_assets"}, {"d": "M1326 457 L1330 457", "elementId": "wealth_assets"}, {"d": "M1334 457 L1343 458", "elementId": "wealth_assets"}, {"d": "M1372 457 L1372 461", "elementId": "wealth_assets"}, {"d": "M1610 457 L1607 462", "elementId": "wealth_assets"}, {"d": "M1370 455 L1361 456", "elementId": "wealth_assets"}, {"d": "M1487 455 L1482 457", "elementId": "wealth_assets"}, {"d": "M1301 454 L1279 469 L1312 473", "elementId": "wealth_assets"}, {"d": "M1307 454 L1312 455", "elementId": "wealth_assets"}, {"d": "M1383 454 L1380 455", "elementId": "wealth_assets"}, {"d": "M1610 454 L1596 455", "elementId": "wealth_assets"}, {"d": "M1406 453 L1406 463", "elementId": "wealth_assets"}, {"d": "M1416 453 L1416 464", "elementId": "wealth_assets"}, {"d": "M1435 453 L1436 466", "elementId": "wealth_assets"}, {"d": "M1648 453 L1658 453", "elementId": "wealth_assets"}, {"d": "M1389 452 L1389 456", "elementId": "wealth_assets"}, {"d": "M1449 452 L1451 464", "elementId": "wealth_assets"}, {"d": "M1398 451 L1397 461", "elementId": "wealth_assets"}, {"d": "M1408 451 L1414 451", "elementId": "wealth_assets"}, {"d": "M1418 451 L1433 451", "elementId": "wealth_assets"}, {"d": "M1625 451 L1616 453", "elementId": "wealth_assets"}, {"d": "M1447 450 L1437 451", "elementId": "wealth_assets"}, {"d": "M1464 450 L1465 456", "elementId": "wealth_assets"}, {"d": "M1400 449 L1405 450", "elementId": "wealth_assets"}, {"d": "M1296 448 L1269 458", "elementId": "wealth_assets"}, {"d": "M1462 448 L1451 450", "elementId": "wealth_assets"}, {"d": "M1609 448 L1613 452", "elementId": "wealth_assets"}, {"d": "M1639 448 L1627 450", "elementId": "wealth_assets"}, {"d": "M1670 448 L1662 451", "elementId": "wealth_assets"}, {"d": "M1394 447 L1390 449", "elementId": "wealth_assets"}, {"d": "M1478 446 L1479 456", "elementId": "wealth_assets"}, {"d": "M1332 445 L1332 455", "elementId": "wealth_assets"}, {"d": "M1322 444 L1322 455", "elementId": "wealth_assets"}, {"d": "M1344 444 L1345 456", "elementId": "wealth_assets"}, {"d": "M1353 444 L1354 454", "elementId": "wealth_assets"}, {"d": "M1476 444 L1465 447", "elementId": "wealth_assets"}, {"d": "M1620 444 L1625 449", "elementId": "wealth_assets"}, {"d": "M1358 443 L1359 454", "elementId": "wealth_assets"}, {"d": "M1682 443 L1673 447", "elementId": "wealth_assets"}, {"d": "M1313 442 L1314 454", "elementId": "wealth_assets"}, {"d": "M1325 442 L1331 442", "elementId": "wealth_assets"}, {"d": "M1342 442 L1334 443", "elementId": "wealth_assets"}, {"d": "M1346 442 L1351 442", "elementId": "wealth_assets"}, {"d": "M1485 442 L1487 452", "elementId": "wealth_assets"}, {"d": "M1307 441 L1307 451", "elementId": "wealth_assets"}, {"d": "M1371 441 L1372 453", "elementId": "wealth_assets"}, {"d": "M1483 441 L1479 442", "elementId": "wealth_assets"}, {"d": "M1653 441 L1658 443", "elementId": "wealth_assets"}, {"d": "M1315 440 L1322 441", "elementId": "wealth_assets"}, {"d": "M1651 440 L1642 446", "elementId": "wealth_assets"}, {"d": "M1369 439 L1360 440", "elementId": "wealth_assets"}, {"d": "M1435 439 L1445 439", "elementId": "wealth_assets"}, {"d": "M1491 439 L1492 447", "elementId": "wealth_assets"}, {"d": "M1677 439 L1682 441", "elementId": "wealth_assets"}, {"d": "M1426 438 L1431 438", "elementId": "wealth_assets"}, {"d": "M1384 437 L1386 449", "elementId": "wealth_assets"}, {"d": "M1457 437 L1448 438", "elementId": "wealth_assets"}, {"d": "M1709 437 L1713 437", "elementId": "wealth_assets"}, {"d": "M1382 436 L1372 438", "elementId": "wealth_assets"}, {"d": "M1417 436 L1422 437", "elementId": "wealth_assets"}, {"d": "M1498 436 L1495 448", "elementId": "wealth_assets"}, {"d": "M1706 436 L1684 442", "elementId": "wealth_assets"}, {"d": "M1406 435 L1403 440", "elementId": "wealth_assets"}, {"d": "M1410 435 L1414 435", "elementId": "wealth_assets"}, {"d": "M1469 435 L1461 436", "elementId": "wealth_assets"}, {"d": "M1663 435 L1663 439", "elementId": "wealth_assets"}, {"d": "M1393 434 L1395 445", "elementId": "wealth_assets"}, {"d": "M1661 433 L1653 439", "elementId": "wealth_assets"}, {"d": "M1391 432 L1384 435", "elementId": "wealth_assets"}, {"d": "M1673 432 L1675 437", "elementId": "wealth_assets"}, {"d": "M1722 432 L1718 434", "elementId": "wealth_assets"}, {"d": "M1289 431 L1294 431", "elementId": "wealth_assets"}, {"d": "M1398 431 L1401 439", "elementId": "wealth_assets"}, {"d": "M1480 431 L1473 433", "elementId": "wealth_assets"}, {"d": "M1278 430 L1285 431", "elementId": "wealth_assets"}, {"d": "M1303 430 L1312 430", "elementId": "wealth_assets"}, {"d": "M1512 430 L1499 433", "elementId": "wealth_assets"}, {"d": "M1667 430 L1671 430", "elementId": "wealth_assets"}, {"d": "M1270 429 L1274 430", "elementId": "wealth_assets"}, {"d": "M1323 428 L1315 429", "elementId": "wealth_assets"}, {"d": "M1404 428 L1405 432", "elementId": "wealth_assets"}, {"d": "M1488 428 L1482 430", "elementId": "wealth_assets"}, {"d": "M1515 428 L1519 428", "elementId": "wealth_assets"}, {"d": "M1402 427 L1398 428", "elementId": "wealth_assets"}, {"d": "M1496 427 L1496 432", "elementId": "wealth_assets"}, {"d": "M1510 425 L1504 428", "elementId": "wealth_assets"}, {"d": "M1556 425 L1587 427", "elementId": "wealth_assets"}, {"d": "M1335 424 L1326 426", "elementId": "wealth_assets"}, {"d": "M1424 424 L1424 435", "elementId": "wealth_assets"}, {"d": "M1433 424 L1433 436", "elementId": "wealth_assets"}, {"d": "M1446 424 L1446 436", "elementId": "wealth_assets"}, {"d": "M1703 424 L1704 428", "elementId": "wealth_assets"}, {"d": "M1459 423 L1459 435", "elementId": "wealth_assets"}, {"d": "M1517 423 L1513 424", "elementId": "wealth_assets"}, {"d": "M1344 422 L1337 423", "elementId": "wealth_assets"}, {"d": "M1347 422 L1352 424", "elementId": "wealth_assets"}, {"d": "M1362 422 L1356 424", "elementId": "wealth_assets"}, {"d": "M1416 422 L1416 433", "elementId": "wealth_assets"}, {"d": "M1426 422 L1431 422", "elementId": "wealth_assets"}, {"d": "M1435 422 L1444 422", "elementId": "wealth_assets"}, {"d": "M1701 422 L1674 429", "elementId": "wealth_assets"}, {"d": "M1783 422 L1753 450 L1700 470", "elementId": "wealth_assets"}, {"d": "M1418 421 L1422 422", "elementId": "wealth_assets"}, {"d": "M1457 421 L1448 422", "elementId": "wealth_assets"}, {"d": "M1471 421 L1471 432", "elementId": "wealth_assets"}, {"d": "M1412 420 L1416 420", "elementId": "wealth_assets"}, {"d": "M1534 420 L1553 424", "elementId": "wealth_assets"}, {"d": "M1469 419 L1461 421", "elementId": "wealth_assets"}, {"d": "M1287 418 L1287 429", "elementId": "wealth_assets"}, {"d": "M1300 418 L1300 429", "elementId": "wealth_assets"}, {"d": "M1356 418 L1362 420", "elementId": "wealth_assets"}, {"d": "M1480 418 L1480 429", "elementId": "wealth_assets"}, {"d": "M1276 417 L1276 428", "elementId": "wealth_assets"}, {"d": "M1313 417 L1313 427", "elementId": "wealth_assets"}, {"d": "M1353 417 L1348 420", "elementId": "wealth_assets"}, {"d": "M1478 417 L1472 418", "elementId": "wealth_assets"}, {"d": "M1485 417 L1485 421", "elementId": "wealth_assets"}, {"d": "M1711 418 L1721 418", "elementId": "wealth_assets"}, {"d": "M1268 416 L1269 426", "elementId": "wealth_assets"}, {"d": "M1289 416 L1298 416", "elementId": "wealth_assets"}, {"d": "M1278 415 L1285 416", "elementId": "wealth_assets"}, {"d": "M1311 415 L1302 416", "elementId": "wealth_assets"}, {"d": "M1324 415 L1324 424", "elementId": "wealth_assets"}, {"d": "M1405 415 L1407 420", "elementId": "wealth_assets"}, {"d": "M1502 415 L1497 423", "elementId": "wealth_assets"}, {"d": "M1270 414 L1274 414", "elementId": "wealth_assets"}, {"d": "M1322 413 L1314 414", "elementId": "wealth_assets"}, {"d": "M1334 413 L1335 422", "elementId": "wealth_assets"}, {"d": "M1363 413 L1388 419 L1373 428 L1329 432", "elementId": "wealth_assets"}, {"d": "M1491 413 L1493 423", "elementId": "wealth_assets"}, {"d": "M1541 414 L1534 417", "elementId": "wealth_assets"}, {"d": "M1263 412 L1267 413", "elementId": "wealth_assets"}, {"d": "M1332 411 L1325 412", "elementId": "wealth_assets"}, {"d": "M1343 409 L1344 419", "elementId": "wealth_assets"}, {"d": "M1514 409 L1526 414", "elementId": "wealth_assets"}, {"d": "M1396 408 L1401 412", "elementId": "wealth_assets"}, {"d": "M1341 407 L1335 409", "elementId": "wealth_assets"}, {"d": "M1499 407 L1491 411", "elementId": "wealth_assets"}, {"d": "M1446 406 L1444 410", "elementId": "wealth_assets"}, {"d": "M1352 405 L1354 414", "elementId": "wealth_assets"}, {"d": "M1370 405 L1390 407", "elementId": "wealth_assets"}, {"d": "M1504 405 L1511 407", "elementId": "wealth_assets"}, {"d": "M1350 404 L1344 406", "elementId": "wealth_assets"}, {"d": "M1438 404 L1445 404", "elementId": "wealth_assets"}, {"d": "M1458 403 L1452 404", "elementId": "wealth_assets"}, {"d": "M1565 402 L1571 406", "elementId": "wealth_assets"}, {"d": "M1359 401 L1360 410", "elementId": "wealth_assets"}, {"d": "M1521 401 L1534 411", "elementId": "wealth_assets"}, {"d": "M1559 401 L1563 402", "elementId": "wealth_assets"}, {"d": "M1439 399 L1443 399", "elementId": "wealth_assets"}, {"d": "M1551 399 L1555 422", "elementId": "wealth_assets"}, {"d": "M1620 399 L1605 414", "elementId": "wealth_assets"}, {"d": "M1295 398 L1310 398", "elementId": "wealth_assets"}, {"d": "M1456 397 L1460 398", "elementId": "wealth_assets"}, {"d": "M1561 397 L1564 400", "elementId": "wealth_assets"}, {"d": "M1401 395 L1396 404", "elementId": "wealth_assets"}, {"d": "M1381 394 L1387 394", "elementId": "wealth_assets"}, {"d": "M1398 393 L1391 394", "elementId": "wealth_assets"}, {"d": "M1412 391 L1404 393", "elementId": "wealth_assets"}, {"d": "M1308 389 L1304 390", "elementId": "wealth_assets"}, {"d": "M1442 412 L1418 410 L1413 403 L1449 389 L1485 396 L1475 406 L1446 412", "elementId": "wealth_assets"}, {"d": "M1641 389 L1645 389", "elementId": "wealth_assets"}, {"d": "M1660 389 L1662 392", "elementId": "wealth_assets"}, {"d": "M1312 388 L1320 390", "elementId": "wealth_assets"}, {"d": "M1424 388 L1415 390", "elementId": "wealth_assets"}, {"d": "M1625 388 L1623 392", "elementId": "wealth_assets"}, {"d": "M1504 387 L1505 396", "elementId": "wealth_assets"}, {"d": "M1658 387 L1647 390", "elementId": "wealth_assets"}, {"d": "M1621 386 L1579 421", "elementId": "wealth_assets"}, {"d": "M1431 385 L1427 386", "elementId": "wealth_assets"}, {"d": "M1772 385 L1735 417", "elementId": "wealth_assets"}, {"d": "M1573 384 L1572 389", "elementId": "wealth_assets"}, {"d": "M1775 384 L1785 386", "elementId": "wealth_assets"}, {"d": "M1439 382 L1434 384", "elementId": "wealth_assets"}, {"d": "M1310 381 L1272 399 L1284 406 L1312 405 L1346 389 L1311 381", "elementId": "wealth_assets"}, {"d": "M1360 381 L1364 393", "elementId": "wealth_assets"}, {"d": "M1373 381 L1374 392", "elementId": "wealth_assets"}, {"d": "M1379 381 L1379 392", "elementId": "wealth_assets"}, {"d": "M1389 381 L1389 392", "elementId": "wealth_assets"}, {"d": "M1468 381 L1444 382", "elementId": "wealth_assets"}, {"d": "M1585 381 L1584 386", "elementId": "wealth_assets"}, {"d": "M1400 380 L1400 391", "elementId": "wealth_assets"}, {"d": "M1473 380 L1489 384", "elementId": "wealth_assets"}, {"d": "M1563 380 L1572 382", "elementId": "wealth_assets"}, {"d": "M1381 379 L1387 379", "elementId": "wealth_assets"}, {"d": "M1560 379 L1553 389", "elementId": "wealth_assets"}, {"d": "M1398 378 L1391 379", "elementId": "wealth_assets"}, {"d": "M1412 378 L1413 388", "elementId": "wealth_assets"}, {"d": "M1631 378 L1627 382", "elementId": "wealth_assets"}, {"d": "M1364 377 L1372 378", "elementId": "wealth_assets"}, {"d": "M1779 377 L1775 381", "elementId": "wealth_assets"}, {"d": "M1781 377 L1785 379", "elementId": "wealth_assets"}, {"d": "M1350 376 L1356 377", "elementId": "wealth_assets"}, {"d": "M1410 376 L1402 377", "elementId": "wealth_assets"}, {"d": "M1423 375 L1424 385", "elementId": "wealth_assets"}, {"d": "M1421 374 L1413 375", "elementId": "wealth_assets"}, {"d": "M1431 373 L1432 382", "elementId": "wealth_assets"}, {"d": "M1455 373 L1470 377", "elementId": "wealth_assets"}, {"d": "M1347 375 L1300 374 L1266 387", "elementId": "wealth_assets"}, {"d": "M1784 372 L1790 372", "elementId": "wealth_assets"}, {"d": "M1429 371 L1424 372", "elementId": "wealth_assets"}, {"d": "M1572 371 L1562 377", "elementId": "wealth_assets"}, {"d": "M1438 370 L1439 379", "elementId": "wealth_assets"}, {"d": "M1575 370 L1584 378", "elementId": "wealth_assets"}, {"d": "M1432 369 L1436 369", "elementId": "wealth_assets"}, {"d": "M1440 369 L1443 376", "elementId": "wealth_assets"}, {"d": "M1785 369 L1792 369", "elementId": "wealth_assets"}, {"d": "M1368 368 L1377 369", "elementId": "wealth_assets"}, {"d": "M1380 368 L1390 368", "elementId": "wealth_assets"}, {"d": "M1348 367 L1349 373", "elementId": "wealth_assets"}, {"d": "M1356 367 L1364 368", "elementId": "wealth_assets"}, {"d": "M1393 367 L1401 367", "elementId": "wealth_assets"}, {"d": "M1786 366 L1793 366", "elementId": "wealth_assets"}, {"d": "M1410 365 L1404 366", "elementId": "wealth_assets"}, {"d": "M1562 363 L1572 368", "elementId": "wealth_assets"}, {"d": "M1450 362 L1445 376", "elementId": "wealth_assets"}, {"d": "M1423 361 L1413 364", "elementId": "wealth_assets"}, {"d": "M1446 361 L1439 366", "elementId": "wealth_assets"}, {"d": "M1550 360 L1556 361", "elementId": "wealth_assets"}, {"d": "M1337 357 L1343 363", "elementId": "wealth_assets"}, {"d": "M1430 357 L1425 359", "elementId": "wealth_assets"}, {"d": "M1366 356 L1366 366", "elementId": "wealth_assets"}, {"d": "M1378 356 L1378 366", "elementId": "wealth_assets"}, {"d": "M1390 356 L1391 365", "elementId": "wealth_assets"}, {"d": "M1402 355 L1402 364", "elementId": "wealth_assets"}, {"d": "M1786 355 L1784 364", "elementId": "wealth_assets"}, {"d": "M1355 354 L1355 364", "elementId": "wealth_assets"}, {"d": "M1368 354 L1376 354", "elementId": "wealth_assets"}, {"d": "M1380 354 L1388 354", "elementId": "wealth_assets"}, {"d": "M1357 353 L1365 353", "elementId": "wealth_assets"}, {"d": "M1400 353 L1392 354", "elementId": "wealth_assets"}, {"d": "M1411 353 L1411 362", "elementId": "wealth_assets"}, {"d": "M1437 352 L1433 355", "elementId": "wealth_assets"}, {"d": "M1346 351 L1345 361", "elementId": "wealth_assets"}, {"d": "M1409 351 L1403 352", "elementId": "wealth_assets"}, {"d": "M1348 350 L1353 351", "elementId": "wealth_assets"}, {"d": "M1421 350 L1423 359", "elementId": "wealth_assets"}, {"d": "M1340 348 L1346 349", "elementId": "wealth_assets"}, {"d": "M1419 348 L1412 350", "elementId": "wealth_assets"}, {"d": "M1429 347 L1430 354", "elementId": "wealth_assets"}, {"d": "M1427 345 L1422 346", "elementId": "wealth_assets"}, {"d": "M1813 345 L1814 368 L1803 393", "elementId": "wealth_assets"}, {"d": "M1435 343 L1437 349", "elementId": "wealth_assets"}, {"d": "M1778 343 L1784 352", "elementId": "wealth_assets"}, {"d": "M1787 341 L1787 352", "elementId": "wealth_assets"}, {"d": "M1500 340 L1542 356", "elementId": "wealth_assets"}, {"d": "M1780 340 L1784 340", "elementId": "wealth_assets"}, {"d": "M1442 339 L1442 346", "elementId": "wealth_assets"}, {"d": "M1439 338 L1435 340", "elementId": "wealth_assets"}, {"d": "M1376 337 L1383 339", "elementId": "wealth_assets"}, {"d": "M1392 336 L1398 336", "elementId": "wealth_assets"}, {"d": "M1481 334 L1484 336", "elementId": "wealth_assets"}, {"d": "M1756 334 L1734 360 L1693 378", "elementId": "wealth_assets"}, {"d": "M1381 333 L1377 335", "elementId": "wealth_assets"}, {"d": "M1784 332 L1786 338", "elementId": "wealth_assets"}, {"d": "M1466 330 L1471 332", "elementId": "wealth_assets"}, {"d": "M1341 329 L1334 338", "elementId": "wealth_assets"}, {"d": "M1390 329 L1384 331", "elementId": "wealth_assets"}, {"d": "M1394 329 L1399 331", "elementId": "wealth_assets"}, {"d": "M1556 328 L1602 349", "elementId": "wealth_assets"}, {"d": "M1767 327 L1777 329", "elementId": "wealth_assets"}, {"d": "M1558 325 L1603 347", "elementId": "wealth_assets"}, {"d": "M1464 324 L1472 327", "elementId": "wealth_assets"}, {"d": "M1662 324 L1647 351", "elementId": "wealth_assets"}, {"d": "M1792 324 L1799 344 L1795 366", "elementId": "wealth_assets"}, {"d": "M1355 323 L1351 324", "elementId": "wealth_assets"}, {"d": "M1383 344 L1362 344 L1352 336 L1383 323 L1423 330 L1415 339 L1387 344", "elementId": "wealth_assets"}, {"d": "M1544 322 L1553 327", "elementId": "wealth_assets"}, {"d": "M1364 320 L1358 321", "elementId": "wealth_assets"}, {"d": "M1457 320 L1443 328", "elementId": "wealth_assets"}, {"d": "M1545 320 L1555 323", "elementId": "wealth_assets"}, {"d": "M1591 319 L1597 321", "elementId": "wealth_assets"}, {"d": "M1783 322 L1768 318 L1765 325", "elementId": "wealth_assets"}, {"d": "M1592 316 L1598 319", "elementId": "wealth_assets"}, {"d": "M1367 319 L1412 315 L1440 328", "elementId": "wealth_assets"}, {"d": "M1582 314 L1588 317", "elementId": "wealth_assets"}, {"d": "M1583 312 L1590 315", "elementId": "wealth_assets"}, {"d": "M1501 306 L1478 327", "elementId": "wealth_assets"}, {"d": "M1563 304 L1570 307", "elementId": "wealth_assets"}, {"d": "M1543 296 L1557 302", "elementId": "wealth_assets"}, {"d": "M1684 294 L1672 315", "elementId": "wealth_assets"}, {"d": "M1360 293 L1354 294", "elementId": "wealth_assets"}, {"d": "M1344 292 L1350 294", "elementId": "wealth_assets"}, {"d": "M1681 291 L1676 296", "elementId": "wealth_assets"}, {"d": "M1335 290 L1341 291", "elementId": "wealth_assets"}, {"d": "M1302 289 L1316 297", "elementId": "wealth_assets"}, {"d": "M1585 289 L1632 310", "elementId": "wealth_assets"}, {"d": "M1636 288 L1645 292", "elementId": "wealth_assets"}, {"d": "M1328 287 L1332 288", "elementId": "wealth_assets"}, {"d": "M1355 286 L1352 292", "elementId": "wealth_assets"}, {"d": "M1345 285 L1343 289", "elementId": "wealth_assets"}, {"d": "M1454 285 L1425 299", "elementId": "wealth_assets"}, {"d": "M1348 284 L1355 284", "elementId": "wealth_assets"}, {"d": "M1321 283 L1325 285", "elementId": "wealth_assets"}, {"d": "M1337 283 L1334 287", "elementId": "wealth_assets"}, {"d": "M1567 282 L1580 286", "elementId": "wealth_assets"}, {"d": "M1340 281 L1345 282", "elementId": "wealth_assets"}, {"d": "M1330 280 L1328 284", "elementId": "wealth_assets"}, {"d": "M1333 278 L1337 280", "elementId": "wealth_assets"}, {"d": "M1324 276 L1321 280", "elementId": "wealth_assets"}, {"d": "M1307 273 L1312 276", "elementId": "wealth_assets"}, {"d": "M1317 271 L1315 275", "elementId": "wealth_assets"}, {"d": "M1321 270 L1325 273", "elementId": "wealth_assets"}, {"d": "M1694 270 L1685 286", "elementId": "wealth_assets"}, {"d": "M1689 269 L1673 291", "elementId": "wealth_assets"}, {"d": "M1311 265 L1308 269", "elementId": "wealth_assets"}, {"d": "M1315 264 L1318 268", "elementId": "wealth_assets"}, {"d": "M1580 264 L1630 284", "elementId": "wealth_assets"}, {"d": "M1300 263 L1305 270", "elementId": "wealth_assets"}, {"d": "M1582 262 L1614 275", "elementId": "wealth_assets"}, {"d": "M1568 258 L1576 260", "elementId": "wealth_assets"}, {"d": "M1296 256 L1298 261", "elementId": "wealth_assets"}, {"d": "M1304 256 L1302 260", "elementId": "wealth_assets"}, {"d": "M1308 255 L1312 262", "elementId": "wealth_assets"}, {"d": "M1541 255 L1521 284", "elementId": "wealth_assets"}, {"d": "M1340 254 L1351 256", "elementId": "wealth_assets"}, {"d": "M1613 252 L1617 254", "elementId": "wealth_assets"}, {"d": "M1300 248 L1297 253", "elementId": "wealth_assets"}, {"d": "M1292 247 L1294 253", "elementId": "wealth_assets"}, {"d": "M1303 247 L1306 253", "elementId": "wealth_assets"}, {"d": "M1348 246 L1353 253", "elementId": "wealth_assets"}, {"d": "M1591 243 L1602 247", "elementId": "wealth_assets"}, {"d": "M1352 242 L1359 248 L1355 254", "elementId": "wealth_assets"}, {"d": "M1298 241 L1294 245", "elementId": "wealth_assets"}, {"d": "M1388 241 L1390 269 L1371 286", "elementId": "wealth_assets"}, {"d": "M1391 239 L1396 253", "elementId": "wealth_assets"}, {"d": "M1722 238 L1699 263", "elementId": "wealth_assets"}, {"d": "M1583 237 L1603 245", "elementId": "wealth_assets"}, {"d": "M1622 233 L1657 249", "elementId": "wealth_assets"}, {"d": "M1341 232 L1345 240", "elementId": "wealth_assets"}, {"d": "M1624 231 L1658 247", "elementId": "wealth_assets"}, {"d": "M1338 230 L1333 237 L1343 242", "elementId": "wealth_assets"}, {"d": "M1342 229 L1350 232", "elementId": "wealth_assets"}, {"d": "M1296 228 L1291 244", "elementId": "wealth_assets"}, {"d": "M1299 228 L1300 238", "elementId": "wealth_assets"}, {"d": "M1739 226 L1734 230", "elementId": "wealth_assets"}, {"d": "M1746 223 L1753 224", "elementId": "wealth_assets"}, {"d": "M1338 222 L1339 228", "elementId": "wealth_assets"}, {"d": "M1296 220 L1296 224", "elementId": "wealth_assets"}, {"d": "M1595 219 L1611 225", "elementId": "wealth_assets"}, {"d": "M1767 218 L1760 225", "elementId": "wealth_assets"}, {"d": "M1765 217 L1759 221", "elementId": "wealth_assets"}, {"d": "M1324 216 L1313 236 L1331 263 L1355 273 L1376 265", "elementId": "wealth_assets"}, {"d": "M1655 216 L1646 217", "elementId": "wealth_assets"}, {"d": "M1340 213 L1363 223 L1378 244", "elementId": "wealth_assets"}, {"d": "M1715 213 L1730 219", "elementId": "wealth_assets"}, {"d": "M1652 212 L1646 214", "elementId": "wealth_assets"}, {"d": "M1744 209 L1743 221", "elementId": "wealth_assets"}, {"d": "M1667 208 L1661 213", "elementId": "wealth_assets"}, {"d": "M1772 206 L1768 215", "elementId": "wealth_assets"}, {"d": "M1467 205 L1460 206", "elementId": "wealth_assets"}, {"d": "M1316 204 L1307 209", "elementId": "wealth_assets"}, {"d": "M1345 203 L1367 212 L1384 231", "elementId": "wealth_assets"}, {"d": "M1435 203 L1457 207", "elementId": "wealth_assets"}, {"d": "M1328 202 L1320 203", "elementId": "wealth_assets"}, {"d": "M1643 202 L1646 210", "elementId": "wealth_assets"}, {"d": "M1690 202 L1704 208", "elementId": "wealth_assets"}, {"d": "M1336 201 L1342 202", "elementId": "wealth_assets"}, {"d": "M1475 201 L1470 202", "elementId": "wealth_assets"}, {"d": "M1670 200 L1669 205", "elementId": "wealth_assets"}, {"d": "M1750 200 L1746 206", "elementId": "wealth_assets"}, {"d": "M1640 199 L1643 215", "elementId": "wealth_assets"}, {"d": "M1327 198 L1322 199", "elementId": "wealth_assets"}, {"d": "M1436 198 L1453 199", "elementId": "wealth_assets"}, {"d": "M1668 198 L1664 203", "elementId": "wealth_assets"}, {"d": "M1464 196 L1456 198", "elementId": "wealth_assets"}, {"d": "M1483 196 L1478 199", "elementId": "wealth_assets"}, {"d": "M1756 196 L1750 210", "elementId": "wealth_assets"}, {"d": "M1746 195 L1752 195", "elementId": "wealth_assets"}, {"d": "M1743 194 L1734 217", "elementId": "wealth_assets"}, {"d": "M1294 192 L1277 213 L1273 232", "elementId": "wealth_assets"}, {"d": "M1670 192 L1670 196", "elementId": "wealth_assets"}, {"d": "M1674 192 L1679 195", "elementId": "wealth_assets"}, {"d": "M1489 191 L1486 193", "elementId": "wealth_assets"}, {"d": "M1477 190 L1473 192", "elementId": "wealth_assets"}, {"d": "M1418 187 L1427 196", "elementId": "wealth_assets"}, {"d": "M1651 186 L1646 192", "elementId": "wealth_assets"}, {"d": "M1654 186 L1668 191", "elementId": "wealth_assets"}, {"d": "M1484 185 L1479 188", "elementId": "wealth_assets"}, {"d": "M1770 185 L1773 200", "elementId": "wealth_assets"}, {"d": "M1496 184 L1492 188", "elementId": "wealth_assets"}, {"d": "M1758 183 L1745 192", "elementId": "wealth_assets"}, {"d": "M1760 183 L1766 185", "elementId": "wealth_assets"}, {"d": "M1645 182 L1651 184", "elementId": "wealth_assets"}, {"d": "M1489 179 L1486 183", "elementId": "wealth_assets"}, {"d": "M1761 179 L1765 180", "elementId": "wealth_assets"}, {"d": "M1637 178 L1641 179", "elementId": "wealth_assets"}, {"d": "M1646 178 L1651 179", "elementId": "wealth_assets"}, {"d": "M1502 176 L1499 181", "elementId": "wealth_assets"}, {"d": "M1494 172 L1492 176", "elementId": "wealth_assets"}, {"d": "M1497 172 L1501 174", "elementId": "wealth_assets"}, {"d": "M1521 171 L1506 196", "elementId": "wealth_assets"}, {"d": "M1505 169 L1503 174", "elementId": "wealth_assets"}, {"d": "M1654 178 L1666 169 L1678 182", "elementId": "wealth_assets"}, {"d": "M1451 168 L1449 172", "elementId": "wealth_assets"}, {"d": "M1600 166 L1545 249", "elementId": "wealth_assets"}, {"d": "M1461 165 L1455 166", "elementId": "wealth_assets"}, {"d": "M1408 164 L1413 184", "elementId": "wealth_assets"}, {"d": "M1602 164 L1606 164", "elementId": "wealth_assets"}, {"d": "M1411 163 L1416 182", "elementId": "wealth_assets"}, {"d": "M1592 162 L1597 163", "elementId": "wealth_assets"}, {"d": "M1424 161 L1424 166", "elementId": "wealth_assets"}, {"d": "M1427 161 L1427 166", "elementId": "wealth_assets"}, {"d": "M1509 161 L1507 167", "elementId": "wealth_assets"}, {"d": "M1501 159 L1500 163", "elementId": "wealth_assets"}, {"d": "M1604 156 L1601 160", "elementId": "wealth_assets"}, {"d": "M1459 154 L1454 164", "elementId": "wealth_assets"}, {"d": "M1489 154 L1471 179 L1454 186 L1437 184 L1426 169", "elementId": "wealth_assets"}, {"d": "M1702 154 L1759 178", "elementId": "wealth_assets"}, {"d": "M1462 153 L1464 162", "elementId": "wealth_assets"}, {"d": "M1410 152 L1410 156", "elementId": "wealth_assets"}, {"d": "M1413 152 L1412 156", "elementId": "wealth_assets"}, {"d": "M1511 150 L1510 158", "elementId": "wealth_assets"}, {"d": "M1684 147 L1688 148", "elementId": "wealth_assets"}, {"d": "M1594 144 L1594 149", "elementId": "wealth_assets"}, {"d": "M1685 143 L1690 145", "elementId": "wealth_assets"}, {"d": "M1673 142 L1681 145", "elementId": "wealth_assets"}, {"d": "M1453 141 L1452 146", "elementId": "wealth_assets"}, {"d": "M1465 140 L1462 147", "elementId": "wealth_assets"}, {"d": "M1469 138 L1472 142", "elementId": "wealth_assets"}, {"d": "M1674 138 L1683 142", "elementId": "wealth_assets"}, {"d": "M1418 137 L1416 141", "elementId": "wealth_assets"}, {"d": "M1458 136 L1465 136", "elementId": "wealth_assets"}, {"d": "M1470 129 L1468 135", "elementId": "wealth_assets"}, {"d": "M1608 129 L1604 132", "elementId": "wealth_assets"}, {"d": "M1605 125 L1601 132", "elementId": "wealth_assets"}, {"d": "M1633 123 L1664 137", "elementId": "wealth_assets"}, {"d": "M1620 122 L1628 124", "elementId": "wealth_assets"}, {"d": "M1617 121 L1611 124", "elementId": "wealth_assets"}, {"d": "M1432 120 L1424 129", "elementId": "wealth_assets"}, {"d": "M1466 119 L1486 128 L1490 149", "elementId": "wealth_assets"}, {"d": "M1464 118 L1442 127 L1427 149", "elementId": "wealth_assets"}, {"d": "M1625 118 L1630 121", "elementId": "wealth_assets"}, {"d": "M1486 109 L1504 128", "elementId": "wealth_assets"}, {"d": "M1454 108 L1445 112", "elementId": "wealth_assets"}, {"d": "M1473 106 L1478 106", "elementId": "wealth_assets"}, {"d": "M1421 105 L1399 130", "elementId": "wealth_assets"}, {"d": "M1454 105 L1444 109", "elementId": "wealth_assets"}, {"d": "M1470 105 L1457 107", "elementId": "wealth_assets"}, {"d": "M1473 103 L1479 103", "elementId": "wealth_assets"}, {"d": "M1505 99 L1521 122", "elementId": "wealth_assets"}]}